streamlit_mock/__init__.py
streamlit_mock/st_aggrid.py
streamlit_mock/streamlit_server_state.py
streamlit_mock/impl/__init__.py
streamlit_mock/impl/mock.py
streamlit_mock/impl/utils.py
streamlit_mock/streamlit/__init__.py
streamlit_mock/streamlit/components/v1/__init__.py
streamlit_mock-0.0.1.dist-info/METADATA
streamlit_mock-0.0.1.dist-info/WHEEL
streamlit_mock-0.0.1.dist-info/licenses/LICENSE
streamlit_mock-0.0.1.dist-info/RECORD
