Metadata-Version: 2.1
Name: streamlit_mock
Version: 0.0.1
Summary: Mocks the stremlit interfaces for unit testing
Project-URL: repository, https://github.com/acschofield/streamlit_mock
Author-email: Andrew Schofield <andrew@schofield.ch>
License: MIT License
Classifier: Development Status :: 3 - Alpha
Classifier: Environment :: Console
Classifier: License :: OSI Approved :: MIT License
Classifier: Operating System :: POSIX :: Linux
Classifier: Programming Language :: Python :: 3
Requires-Python: >=3.8
Requires-Dist: addict
